{
  "url": "https://store.epicgames.com/en-US/p/star-atlas-bead34",
  "title": "Star Atlas",
  "developer": "ATMTA, Inc.",
  "publisher": "ATMTA, Inc.",
  "releaseDate": "N/A",
  "platform": "Windows",
  "genres": [
    "RPG",
    "Strategy"
  ],
  "features": [
    "Controller Support",
    "Online Multiplayer",
    "Single Player"
  ],
  "playerRating": "4.8",
  "description": "What is Star Atlas?\n\nStar Atlas is an upcoming open-world MMORPG based in the year 2620. In the distant future, three major factions have emerged: (1) the MUD Territory governed by humankind, (2) the ONI Region governed by a consortium of alien races, and (3) the Ustur Sector controlled by sentient androids. These factions are in an ongoing struggle for resources, territorial conquest, and political domination. You, a faction citizen of Star Atlas, will have the ability to influence the outcome of this intergalactic conflict while creating the opportunity to earn rewards for your contributions.\n\nOur philosophy is to truly give ‘Power to the People’ by creating a fully immersive MMO gaming and metaverse experience which:\n\nProvides real-world ownership of your in-game assets through blockchain technology which you can continuously expand through your chosen profession and gameplay.\n\nEnables our community to be as close as possible to the development of the game by having tight feedback loops for each gameplay module being released.\n\nProvides the opportunity to our community to co-create the vast metaverse of Star Atlas for the benefit of the whole ecosystem.\n\nState of the game\n\nStar Atlas is currently in development and will be released iteratively through game modules in both web and Unreal Engine 5 which allows the game to continuously expand while the community immerses themselves in the Star Atlas gaming and co-creation experience. The first of the Unreal Engine 5 game modules is the Showroom.\n\nFind out more about Star Atlas at: staratlas.com\n\nLatest Update - Pre-Season (R2)\n\nThe current stage of Showroom is a closed, pre-alpha testing version set at Volant Station. Players can control several different characters to explore an extended landscape and a ground race track by walking or flying around in 6 vehicles/ships.\n\nYou will be able to race against time in one of the 6 currently flyable ships on the Volant Station Showroom race track.\n\nOverall highlights of R2.1:\n\nGround Racing single player with shooting\n\n11 raceable, 49 flyable ships\n\nUE5 in-game marketplace for ships\n\nTest flight of ships not owned + ships becoming available free to test in a cycle\n\nJetpacking - base tier (feet thrusters only)\n\nPhotographer career mode - tier 0\n\nTrain station activated\n\nPerformance improvements and optimization\n\nMain menu ship selection\n\nRacing bug fixes\n\nDogfight updated (level update)\n\nExperimental mode toggle\n\nExplore Outpost 39 & ONI CSS Blockout levels\n\nExplore the future MUD CSS expansion of Volant Station\n\nView upcoming character species variants\n\nGameplay\n\nThe Showroom now offers two fun and experiential ways to improve your flying and combat skills via the Dogfighting & Race Track mini-games.\n\nDogfighting\n\nBattle waves of computer-controlled enemies (available to anyone)\n\nEnemies attack in a range of ships with different levels of strengths in speed, elusiveness and weaponry\n\nPlayers receive a score upon completion\n\nScoreboard tracks current leaders and all time scores\n\nRacing\n\nActivate ground race track (available to anyone)\n\nPlayers receive a score upon completion\n\nSeparate leaderboards to track players’ scores against each other\n\nScoreboard tracks current leaders and all time scores\n\nCharacters\n\nChoose from 4 different characters, including the original pilot, Captain Asha.\n\nFor a limited time, players can select from a number of free skins (not owned NFTs).\n\nA character selection screen replaces the main menu.\n\nThese characters will work solo or in multiplayer situations.\n\nShips\n\nAny explorer can summon a Floyd Liner to fly and a Pearce X4 for dogfights and racing - all for free.\n\nOwners of a Pearce X4, Calico Medtech, Fimbul Airbike, Opal Jet, Opal Jetjet, Fimbul Lowbie and Fimbul ECOS Unibomba can fly them around Volant Station and race against time on the Ground Racetrack.\n\nFor the Floyd Liner, Calico MedTech, Pearce X6 and more, explorers can open ramps, elevators, and doors, and fly around the Showroom environments. The full interior of these ships are walkable during flight in multiplayer mode. Disclaimer: this is currently still in early stage development.\n\nAll other ships are accessible for owners in partially rendered, clay form.\n\nThe latest versions of ships in the pipeline are now visible in the Showroom.\n\nComing soon - Pre-Season\n\nShip cargo and hauling\n\nLooting and skins crafting with ability to sell it on the marketplace\n\nWarp Gates\n\nECOS PvE Attack\n\nAdditional PvP Modes",
  "saved_images": [
    "cover.jpg",
    "screenshot-1.svg",
    "screenshot-2.svg",
    "screenshot-3.jpg",
    "screenshot-4.png",
    "screenshot-5.png",
    "screenshot-6.png",
    "screenshot-7.png",
    "screenshot-8.png",
    "screenshot-9.png",
    "screenshot-10.png"
  ],
  "newPrice": "Unknown Price"
}